[
  {
    "Season": 2017,
    "SeasonType": 1,
    "TeamID": 10,
    "Key": "CLE",
    "City": "Cleveland",
    "Name": "Indians",
    "League": "AL",
    "Division": "Central",
    "Wins": 110,
    "Losses": 66,
    "Percentage": 0.7,
    "DivisionWins": 51,
    "DivisionLosses": 28,
    "GamesBehind": null,
    "LastTenGamesWins": 7,
    "LastTenGamesLosses": 3,
    "Streak": "Scrambled",
    "WildCardRank": null,
    "WildCardGamesBehind": null,
    "HomeWins": 50,
    "HomeLosses": 34,
    "AwayWins": 59,
    "AwayLosses": 31,
    "DayWins": 41,
    "DayLosses": 19,
    "NightWins": 68,
    "NightLosses": 47
  },
  {
    "Season": 2017,
    "SeasonType": 1,
    "TeamID": 20,
    "Key": "MIN",
    "City": "Minnesota",
    "Name": "Twins",
    "League": "AL",
    "Division": "Central",
    "Wins": 93,
    "Losses": 83,
    "Percentage": 0.6,
    "DivisionWins": 43,
    "DivisionLosses": 36,
    "GamesBehind": 16.9,
    "LastTenGamesWins": 6,
    "LastTenGamesLosses": 4,
    "Streak": "Scrambled",
    "WildCardRank": 2,
    "WildCardGamesBehind": 0,
    "HomeWins": 43,
    "HomeLosses": 43,
    "AwayWins": 49,
    "AwayLosses": 39,
    "DayWins": 30,
    "DayLosses": 36,
    "NightWins": 63,
    "NightLosses": 47
  },
  {
    "Season": 2017,
    "SeasonType": 1,
    "TeamID": 5,
    "Key": "KC",
    "City": "Kansas City",
    "Name": "Royals",
    "League": "AL",
    "Division": "Central",
    "Wins": 86,
    "Losses": 90,
    "Percentage": 0.6,
    "DivisionWins": 38,
    "DivisionLosses": 45,
    "GamesBehind": 23.7,
    "LastTenGamesWins": 4,
    "LastTenGamesLosses": 6,
    "Streak": "Scrambled",
    "WildCardRank": 4,
    "WildCardGamesBehind": 6.8,
    "HomeWins": 45,
    "HomeLosses": 40,
    "AwayWins": 41,
    "AwayLosses": 49,
    "DayWins": 29,
    "DayLosses": 29,
    "NightWins": 57,
    "NightLosses": 60
  },
  {
    "Season": 2017,
    "SeasonType": 1,
    "TeamID": 16,
    "Key": "CHW",
    "City": "Chicago",
    "Name": "White Sox",
    "League": "AL",
    "Division": "Central",
    "Wins": 72,
    "Losses": 104,
    "Percentage": 0.5,
    "DivisionWins": 36,
    "DivisionLosses": 46,
    "GamesBehind": 38.3,
    "LastTenGamesWins": 5,
    "LastTenGamesLosses": 5,
    "Streak": "Scrambled",
    "WildCardRank": 12,
    "WildCardGamesBehind": 21.4,
    "HomeWins": 41,
    "HomeLosses": 47,
    "AwayWins": 30,
    "AwayLosses": 57,
    "DayWins": 28,
    "DayLosses": 31,
    "NightWins": 43,
    "NightLosses": 73
  },
  {
    "Season": 2017,
    "SeasonType": 1,
    "TeamID": 17,
    "Key": "DET",
    "City": "Detroit",
    "Name": "Tigers",
    "League": "AL",
    "Division": "Central",
    "Wins": 69,
    "Losses": 107,
    "Percentage": 0.4,
    "DivisionWins": 32,
    "DivisionLosses": 47,
    "GamesBehind": 40.6,
    "LastTenGamesWins": 1,
    "LastTenGamesLosses": 10,
    "Streak": "Scrambled",
    "WildCardRank": 13,
    "WildCardGamesBehind": 23.7,
    "HomeWins": 38,
    "HomeLosses": 52,
    "AwayWins": 31,
    "AwayLosses": 54,
    "DayWins": 30,
    "DayLosses": 32,
    "NightWins": 39,
    "NightLosses": 74
  },
  {
    "Season": 2017,
    "SeasonType": 1,
    "TeamID": 25,
    "Key": "BOS",
    "City": "Boston",
    "Name": "Red Sox",
    "League": "AL",
    "Division": "East",
    "Wins": 102,
    "Losses": 74,
    "Percentage": 0.7,
    "DivisionWins": 45,
    "DivisionLosses": 39,
    "GamesBehind": null,
    "LastTenGamesWins": 7,
    "LastTenGamesLosses": 3,
    "Streak": "Scrambled",
    "WildCardRank": null,
    "WildCardGamesBehind": null,
    "HomeWins": 51,
    "HomeLosses": 33,
    "AwayWins": 50,
    "AwayLosses": 40,
    "DayWins": 27,
    "DayLosses": 24,
    "NightWins": 75,
    "NightLosses": 49
  },
  {
    "Season": 2017,
    "SeasonType": 1,
    "TeamID": 29,
    "Key": "NYY",
    "City": "New York",
    "Name": "Yankees",
    "League": "AL",
    "Division": "East",
    "Wins": 99,
    "Losses": 77,
    "Percentage": 0.6,
    "DivisionWins": 46,
    "DivisionLosses": 33,
    "GamesBehind": 3.4,
    "LastTenGamesWins": 7,
    "LastTenGamesLosses": 3,
    "Streak": "Scrambled",
    "WildCardRank": 1,
    "WildCardGamesBehind": 0,
    "HomeWins": 54,
    "HomeLosses": 31,
    "AwayWins": 45,
    "AwayLosses": 46,
    "DayWins": 36,
    "DayLosses": 29,
    "NightWins": 63,
    "NightLosses": 48
  },
  {
    "Season": 2017,
    "SeasonType": 1,
    "TeamID": 11,
    "Key": "TB",
    "City": "Tampa Bay",
    "Name": "Rays",
    "League": "AL",
    "Division": "East",
    "Wins": 85,
    "Losses": 91,
    "Percentage": 0.5,
    "DivisionWins": 34,
    "DivisionLosses": 45,
    "GamesBehind": 16.9,
    "LastTenGamesWins": 4,
    "LastTenGamesLosses": 6,
    "Streak": "Scrambled",
    "WildCardRank": 6,
    "WildCardGamesBehind": 7.9,
    "HomeWins": 43,
    "HomeLosses": 43,
    "AwayWins": 41,
    "AwayLosses": 47,
    "DayWins": 29,
    "DayLosses": 32,
    "NightWins": 56,
    "NightLosses": 58
  },
  {
    "Season": 2017,
    "SeasonType": 1,
    "TeamID": 3,
    "Key": "TOR",
    "City": "Toronto",
    "Name": "Blue Jays",
    "League": "AL",
    "Division": "East",
    "Wins": 84,
    "Losses": 93,
    "Percentage": 0.5,
    "DivisionWins": 36,
    "DivisionLosses": 45,
    "GamesBehind": 18.6,
    "LastTenGamesWins": 6,
    "LastTenGamesLosses": 4,
    "Streak": "Scrambled",
    "WildCardRank": 10,
    "WildCardGamesBehind": 9.6,
    "HomeWins": 47,
    "HomeLosses": 43,
    "AwayWins": 37,
    "AwayLosses": 49,
    "DayWins": 33,
    "DayLosses": 30,
    "NightWins": 50,
    "NightLosses": 63
  },
  {
    "Season": 2017,
    "SeasonType": 1,
    "TeamID": 19,
    "Key": "BAL",
    "City": "Baltimore",
    "Name": "Orioles",
    "League": "AL",
    "Division": "East",
    "Wins": 84,
    "Losses": 93,
    "Percentage": 0.5,
    "DivisionWins": 41,
    "DivisionLosses": 40,
    "GamesBehind": 18.6,
    "LastTenGamesWins": 3,
    "LastTenGamesLosses": 7,
    "Streak": "Scrambled",
    "WildCardRank": 9,
    "WildCardGamesBehind": 9.6,
    "HomeWins": 51,
    "HomeLosses": 39,
    "AwayWins": 32,
    "AwayLosses": 54,
    "DayWins": 25,
    "DayLosses": 28,
    "NightWins": 58,
    "NightLosses": 65
  },
  {
    "Season": 2017,
    "SeasonType": 1,
    "TeamID": 30,
    "Key": "HOU",
    "City": "Houston",
    "Name": "Astros",
    "League": "AL",
    "Division": "West",
    "Wins": 110,
    "Losses": 67,
    "Percentage": 0.7,
    "DivisionWins": 55,
    "DivisionLosses": 29,
    "GamesBehind": null,
    "LastTenGamesWins": 9,
    "LastTenGamesLosses": 2,
    "Streak": "Scrambled",
    "WildCardRank": null,
    "WildCardGamesBehind": null,
    "HomeWins": 54,
    "HomeLosses": 37,
    "AwayWins": 56,
    "AwayLosses": 30,
    "DayWins": 36,
    "DayLosses": 16,
    "NightWins": 74,
    "NightLosses": 50
  },
  {
    "Season": 2017,
    "SeasonType": 1,
    "TeamID": 21,
    "Key": "LAA",
    "City": "Los Angeles",
    "Name": "Angels",
    "League": "AL",
    "Division": "West",
    "Wins": 87,
    "Losses": 89,
    "Percentage": 0.6,
    "DivisionWins": 41,
    "DivisionLosses": 40,
    "GamesBehind": 22,
    "LastTenGamesWins": 3,
    "LastTenGamesLosses": 7,
    "Streak": "Scrambled",
    "WildCardRank": 3,
    "WildCardGamesBehind": 5.6,
    "HomeWins": 46,
    "HomeLosses": 41,
    "AwayWins": 41,
    "AwayLosses": 47,
    "DayWins": 20,
    "DayLosses": 25,
    "NightWins": 67,
    "NightLosses": 63
  },
  {
    "Season": 2017,
    "SeasonType": 1,
    "TeamID": 13,
    "Key": "SEA",
    "City": "Seattle",
    "Name": "Mariners",
    "League": "AL",
    "Division": "West",
    "Wins": 86,
    "Losses": 92,
    "Percentage": 0.5,
    "DivisionWins": 38,
    "DivisionLosses": 41,
    "GamesBehind": 24.2,
    "LastTenGamesWins": 3,
    "LastTenGamesLosses": 7,
    "Streak": "Scrambled",
    "WildCardRank": 5,
    "WildCardGamesBehind": 7.9,
    "HomeWins": 45,
    "HomeLosses": 46,
    "AwayWins": 41,
    "AwayLosses": 46,
    "DayWins": 24,
    "DayLosses": 33,
    "NightWins": 61,
    "NightLosses": 58
  },
  {
    "Season": 2017,
    "SeasonType": 1,
    "TeamID": 28,
    "Key": "TEX",
    "City": "Texas",
    "Name": "Rangers",
    "League": "AL",
    "Division": "West",
    "Wins": 85,
    "Losses": 92,
    "Percentage": 0.5,
    "DivisionWins": 36,
    "DivisionLosses": 45,
    "GamesBehind": 24.8,
    "LastTenGamesWins": 4,
    "LastTenGamesLosses": 6,
    "Streak": "Scrambled",
    "WildCardRank": 7,
    "WildCardGamesBehind": 8.5,
    "HomeWins": 43,
    "HomeLosses": 42,
    "AwayWins": 41,
    "AwayLosses": 49,
    "DayWins": 22,
    "DayLosses": 24,
    "NightWins": 63,
    "NightLosses": 67
  },
  {
    "Season": 2017,
    "SeasonType": 1,
    "TeamID": 24,
    "Key": "OAK",
    "City": "Oakland",
    "Name": "Athletics",
    "League": "AL",
    "Division": "West",
    "Wins": 82,
    "Losses": 95,
    "Percentage": 0.5,
    "DivisionWins": 32,
    "DivisionLosses": 47,
    "GamesBehind": 28.2,
    "LastTenGamesWins": 9,
    "LastTenGamesLosses": 2,
    "Streak": "Scrambled",
    "WildCardRank": 11,
    "WildCardGamesBehind": 11.8,
    "HomeWins": 51,
    "HomeLosses": 39,
    "AwayWins": 30,
    "AwayLosses": 56,
    "DayWins": 38,
    "DayLosses": 30,
    "NightWins": 43,
    "NightLosses": 65
  },
  {
    "Season": 2017,
    "SeasonType": 1,
    "TeamID": 9,
    "Key": "CHC",
    "City": "Chicago",
    "Name": "Cubs",
    "League": "NL",
    "Division": "Central",
    "Wins": 99,
    "Losses": 77,
    "Percentage": 0.6,
    "DivisionWins": 47,
    "DivisionLosses": 32,
    "GamesBehind": null,
    "LastTenGamesWins": 7,
    "LastTenGamesLosses": 3,
    "Streak": "Scrambled",
    "WildCardRank": null,
    "WildCardGamesBehind": null,
    "HomeWins": 51,
    "HomeLosses": 36,
    "AwayWins": 47,
    "AwayLosses": 41,
    "DayWins": 39,
    "DayLosses": 39,
    "NightWins": 59,
    "NightLosses": 38
  },
  {
    "Season": 2017,
    "SeasonType": 1,
    "TeamID": 32,
    "Key": "MIL",
    "City": "Milwaukee",
    "Name": "Brewers",
    "League": "NL",
    "Division": "Central",
    "Wins": 93,
    "Losses": 83,
    "Percentage": 0.6,
    "DivisionWins": 41,
    "DivisionLosses": 38,
    "GamesBehind": 5.6,
    "LastTenGamesWins": 5,
    "LastTenGamesLosses": 5,
    "Streak": "Scrambled",
    "WildCardRank": 3,
    "WildCardGamesBehind": 2.3,
    "HomeWins": 48,
    "HomeLosses": 40,
    "AwayWins": 45,
    "AwayLosses": 42,
    "DayWins": 33,
    "DayLosses": 31,
    "NightWins": 59,
    "NightLosses": 51
  },
  {
    "Season": 2017,
    "SeasonType": 1,
    "TeamID": 31,
    "Key": "STL",
    "City": "St. Louis",
    "Name": "Cardinals",
    "League": "NL",
    "Division": "Central",
    "Wins": 92,
    "Losses": 84,
    "Percentage": 0.6,
    "DivisionWins": 37,
    "DivisionLosses": 42,
    "GamesBehind": 6.8,
    "LastTenGamesWins": 5,
    "LastTenGamesLosses": 5,
    "Streak": "Scrambled",
    "WildCardRank": 4,
    "WildCardGamesBehind": 3.4,
    "HomeWins": 48,
    "HomeLosses": 37,
    "AwayWins": 43,
    "AwayLosses": 47,
    "DayWins": 28,
    "DayLosses": 29,
    "NightWins": 64,
    "NightLosses": 55
  },
  {
    "Season": 2017,
    "SeasonType": 1,
    "TeamID": 4,
    "Key": "PIT",
    "City": "Pittsburgh",
    "Name": "Pirates",
    "League": "NL",
    "Division": "Central",
    "Wins": 81,
    "Losses": 95,
    "Percentage": 0.5,
    "DivisionWins": 37,
    "DivisionLosses": 48,
    "GamesBehind": 18,
    "LastTenGamesWins": 4,
    "LastTenGamesLosses": 6,
    "Streak": "Scrambled",
    "WildCardRank": 6,
    "WildCardGamesBehind": 14.7,
    "HomeWins": 48,
    "HomeLosses": 41,
    "AwayWins": 32,
    "AwayLosses": 54,
    "DayWins": 30,
    "DayLosses": 24,
    "NightWins": 50,
    "NightLosses": 71
  },
  {
    "Season": 2017,
    "SeasonType": 1,
    "TeamID": 2,
    "Key": "CIN",
    "City": "Cincinnati",
    "Name": "Reds",
    "League": "NL",
    "Division": "Central",
    "Wins": 74,
    "Losses": 102,
    "Percentage": 0.5,
    "DivisionWins": 39,
    "DivisionLosses": 40,
    "GamesBehind": 24.8,
    "LastTenGamesWins": 3,
    "LastTenGamesLosses": 7,
    "Streak": "Scrambled",
    "WildCardRank": 11,
    "WildCardGamesBehind": 21.4,
    "HomeWins": 43,
    "HomeLosses": 47,
    "AwayWins": 30,
    "AwayLosses": 55,
    "DayWins": 27,
    "DayLosses": 37,
    "NightWins": 47,
    "NightLosses": 65
  },
  {
    "Season": 2017,
    "SeasonType": 1,
    "TeamID": 35,
    "Key": "WSH",
    "City": "Washington",
    "Name": "Nationals",
    "League": "NL",
    "Division": "East",
    "Wins": 107,
    "Losses": 69,
    "Percentage": 0.7,
    "DivisionWins": 52,
    "DivisionLosses": 31,
    "GamesBehind": null,
    "LastTenGamesWins": 6,
    "LastTenGamesLosses": 4,
    "Streak": "Scrambled",
    "WildCardRank": null,
    "WildCardGamesBehind": null,
    "HomeWins": 50,
    "HomeLosses": 36,
    "AwayWins": 56,
    "AwayLosses": 33,
    "DayWins": 30,
    "DayLosses": 31,
    "NightWins": 76,
    "NightLosses": 38
  },
  {
    "Season": 2017,
    "SeasonType": 1,
    "TeamID": 22,
    "Key": "MIA",
    "City": "Miami",
    "Name": "Marlins",
    "League": "NL",
    "Division": "East",
    "Wins": 83,
    "Losses": 94,
    "Percentage": 0.5,
    "DivisionWins": 34,
    "DivisionLosses": 46,
    "GamesBehind": 24.2,
    "LastTenGamesWins": 5,
    "LastTenGamesLosses": 5,
    "Streak": "Scrambled",
    "WildCardRank": 5,
    "WildCardGamesBehind": 13,
    "HomeWins": 45,
    "HomeLosses": 41,
    "AwayWins": 38,
    "AwayLosses": 52,
    "DayWins": 25,
    "DayLosses": 27,
    "NightWins": 57,
    "NightLosses": 67
  },
  {
    "Season": 2017,
    "SeasonType": 1,
    "TeamID": 26,
    "Key": "ATL",
    "City": "Atlanta",
    "Name": "Braves",
    "League": "NL",
    "Division": "East",
    "Wins": 80,
    "Losses": 96,
    "Percentage": 0.5,
    "DivisionWins": 36,
    "DivisionLosses": 43,
    "GamesBehind": 27,
    "LastTenGamesWins": 4,
    "LastTenGamesLosses": 6,
    "Streak": "Scrambled",
    "WildCardRank": 7,
    "WildCardGamesBehind": 15.8,
    "HomeWins": 41,
    "HomeLosses": 49,
    "AwayWins": 38,
    "AwayLosses": 47,
    "DayWins": 23,
    "DayLosses": 30,
    "NightWins": 56,
    "NightLosses": 66
  },
  {
    "Season": 2017,
    "SeasonType": 1,
    "TeamID": 18,
    "Key": "NYM",
    "City": "New York",
    "Name": "Mets",
    "League": "NL",
    "Division": "East",
    "Wins": 76,
    "Losses": 101,
    "Percentage": 0.5,
    "DivisionWins": 39,
    "DivisionLosses": 41,
    "GamesBehind": 31,
    "LastTenGamesWins": 4,
    "LastTenGamesLosses": 6,
    "Streak": "Scrambled",
    "WildCardRank": 10,
    "WildCardGamesBehind": 19.7,
    "HomeWins": 40,
    "HomeLosses": 49,
    "AwayWins": 36,
    "AwayLosses": 51,
    "DayWins": 15,
    "DayLosses": 36,
    "NightWins": 60,
    "NightLosses": 65
  },
  {
    "Season": 2017,
    "SeasonType": 1,
    "TeamID": 12,
    "Key": "PHI",
    "City": "Philadelphia",
    "Name": "Phillies",
    "League": "NL",
    "Division": "East",
    "Wins": 71,
    "Losses": 107,
    "Percentage": 0.4,
    "DivisionWins": 40,
    "DivisionLosses": 40,
    "GamesBehind": 36.6,
    "LastTenGamesWins": 5,
    "LastTenGamesLosses": 5,
    "Streak": "Scrambled",
    "WildCardRank": 12,
    "WildCardGamesBehind": 25.4,
    "HomeWins": 40,
    "HomeLosses": 46,
    "AwayWins": 30,
    "AwayLosses": 60,
    "DayWins": 28,
    "DayLosses": 33,
    "NightWins": 42,
    "NightLosses": 73
  },
  {
    "Season": 2017,
    "SeasonType": 1,
    "TeamID": 1,
    "Key": "LAD",
    "City": "Los Angeles",
    "Name": "Dodgers",
    "League": "NL",
    "Division": "West",
    "Wins": 113,
    "Losses": 64,
    "Percentage": 0.7,
    "DivisionWins": 42,
    "DivisionLosses": 38,
    "GamesBehind": null,
    "LastTenGamesWins": 5,
    "LastTenGamesLosses": 5,
    "Streak": "Scrambled",
    "WildCardRank": null,
    "WildCardGamesBehind": null,
    "HomeWins": 63,
    "HomeLosses": 27,
    "AwayWins": 50,
    "AwayLosses": 37,
    "DayWins": 32,
    "DayLosses": 15,
    "NightWins": 81,
    "NightLosses": 48
  },
  {
    "Season": 2017,
    "SeasonType": 1,
    "TeamID": 14,
    "Key": "ARI",
    "City": "Arizona",
    "Name": "Diamondbacks",
    "League": "NL",
    "Division": "West",
    "Wins": 103,
    "Losses": 75,
    "Percentage": 0.7,
    "DivisionWins": 49,
    "DivisionLosses": 34,
    "GamesBehind": 10.7,
    "LastTenGamesWins": 5,
    "LastTenGamesLosses": 5,
    "Streak": "Scrambled",
    "WildCardRank": 1,
    "WildCardGamesBehind": 0,
    "HomeWins": 58,
    "HomeLosses": 32,
    "AwayWins": 45,
    "AwayLosses": 42,
    "DayWins": 30,
    "DayLosses": 23,
    "NightWins": 73,
    "NightLosses": 51
  },
  {
    "Season": 2017,
    "SeasonType": 1,
    "TeamID": 23,
    "Key": "COL",
    "City": "Colorado",
    "Name": "Rockies",
    "League": "NL",
    "Division": "West",
    "Wins": 96,
    "Losses": 82,
    "Percentage": 0.6,
    "DivisionWins": 46,
    "DivisionLosses": 36,
    "GamesBehind": 17.5,
    "LastTenGamesWins": 4,
    "LastTenGamesLosses": 6,
    "Streak": "Scrambled",
    "WildCardRank": 2,
    "WildCardGamesBehind": 0,
    "HomeWins": 50,
    "HomeLosses": 37,
    "AwayWins": 46,
    "AwayLosses": 45,
    "DayWins": 39,
    "DayLosses": 24,
    "NightWins": 57,
    "NightLosses": 57
  },
  {
    "Season": 2017,
    "SeasonType": 1,
    "TeamID": 33,
    "Key": "SD",
    "City": "San Diego",
    "Name": "Padres",
    "League": "NL",
    "Division": "West",
    "Wins": 78,
    "Losses": 99,
    "Percentage": 0.5,
    "DivisionWins": 36,
    "DivisionLosses": 45,
    "GamesBehind": 34.9,
    "LastTenGamesWins": 5,
    "LastTenGamesLosses": 5,
    "Streak": "Scrambled",
    "WildCardRank": 9,
    "WildCardGamesBehind": 17.5,
    "HomeWins": 48,
    "HomeLosses": 42,
    "AwayWins": 30,
    "AwayLosses": 56,
    "DayWins": 20,
    "DayLosses": 33,
    "NightWins": 58,
    "NightLosses": 65
  },
  {
    "Season": 2017,
    "SeasonType": 1,
    "TeamID": 15,
    "Key": "SF",
    "City": "San Francisco",
    "Name": "Giants",
    "League": "NL",
    "Division": "West",
    "Wins": 69,
    "Losses": 109,
    "Percentage": 0.4,
    "DivisionWins": 30,
    "DivisionLosses": 50,
    "GamesBehind": 44.5,
    "LastTenGamesWins": 5,
    "LastTenGamesLosses": 5,
    "Streak": "Scrambled",
    "WildCardRank": 13,
    "WildCardGamesBehind": 27,
    "HomeWins": 40,
    "HomeLosses": 47,
    "AwayWins": 29,
    "AwayLosses": 61,
    "DayWins": 23,
    "DayLosses": 38,
    "NightWins": 46,
    "NightLosses": 71
  }
]
